infrared_tempest-3.0.0.dist-info/DESCRIPTION.rst
infrared_tempest-3.0.0.dist-info/METADATA
infrared_tempest-3.0.0.dist-info/RECORD
infrared_tempest-3.0.0.dist-info/WHEEL
infrared_tempest-3.0.0.dist-info/entry_points.txt
infrared_tempest-3.0.0.dist-info/metadata.json
infrared_tempest-3.0.0.dist-info/pbr.json
infrared_tempest-3.0.0.dist-info/top_level.txt
tempest/__init__.py
tempest/main.yml
tempest/plugin.spec
tempest/tasks/collect-ansible-facts.yml
tempest/tasks/run_suite.yml
tempest/tasks/configure/main.yml
tempest/tasks/configure/run.yml
tempest/tasks/configure/method/git.yml
tempest/tasks/configure/method/git_legacy.yml
tempest/tasks/configure/method/pip.yml
tempest/tasks/configure/method/rpm.yml
tempest/tasks/image/main.yml
tempest/tasks/pre/main.yml
tempest/tasks/pre/packstack.yml
tempest/tasks/pre/tripleo.yml
tempest/tasks/setup/main.yml
tempest/tasks/setup/git/install_plugins.yml
tempest/tasks/setup/git/main.yml
tempest/tasks/setup/pip/install_plugins.yml
tempest/tasks/setup/pip/main.yml
tempest/tasks/setup/rpm/install_plugins.yml
tempest/tasks/setup/rpm/install_plugins_source.yml
tempest/tasks/setup/rpm/main.yml
tempest/vars/venv.yml
tempest/vars/config/git.yml
tempest/vars/setup/git.yml
tempest/vars/setup/pip.yml
tempest/vars/setup/rpm.yml
tempest/vars/tests/all.yml
tempest/vars/tests/baremetal.yml
tempest/vars/tests/compute.yml
tempest/vars/tests/data_processing-tempest.yml
tempest/vars/tests/data_processing.yml
tempest/vars/tests/database.yml
tempest/vars/tests/ec2api.yml
tempest/vars/tests/full.yml
tempest/vars/tests/heat.yml
tempest/vars/tests/identity.yml
tempest/vars/tests/image.yml
tempest/vars/tests/ironic.yml
tempest/vars/tests/ironic_inspector.yml
tempest/vars/tests/kuryr.yml
tempest/vars/tests/manila.yml
tempest/vars/tests/minimal.yml
tempest/vars/tests/network.yml
tempest/vars/tests/networking_bgpvpn.yml
tempest/vars/tests/networking_l2gw.yml
tempest/vars/tests/neutron.yml
tempest/vars/tests/neutron_coverage.yml
tempest/vars/tests/neutron_lbaas.yml
tempest/vars/tests/neutron_qe_sriov.yml
tempest/vars/tests/none.yml
tempest/vars/tests/object_storage.yml
tempest/vars/tests/octavia.yml
tempest/vars/tests/opendaylight_osp10.yml
tempest/vars/tests/opendaylight_osp11.yml
tempest/vars/tests/opendaylight_osp12.yml
